Workbook

Sheet Casos de Prueba
A1: Casos de prueba manuales
A3: ID | B3: Funcionalidad | C3: Tipo | D3: Requiere sesion | E3: Objetivo | F3: Precondiciones | G3: Datos de prueba | H3: Pasos | I3: Resultado esperado | J3: Resultado obtenido | K3: Estado | L3: Evidencia (archivo)
A4: CP-01 | B4: Crear cuenta | C4: Positivo | D4: No | E4: Verificar que se puede crear una cuenta nueva con datos validos | F4: No tener cuenta con ese correo | G4: Correo nuevo + contrasena + repetir contrasena | H4: 1. Abrir despensalo.cl 2. Click en la pestana Crear cuenta 3. Completar correo, contrasena y repetir contrasena 4. Click en Crear mi cuenta | I4: Crea la cuenta y da acceso a la aplicacion | J4: Crea la cuenta e ingresa directo al Resumen. No solicita reingresar credenciales ni envia correo de confirmacion. | K4: Aprobado | L4: CP-01_cuenta_creada.png
A5: CP-02 | B5: Crear cuenta | C5: Negativo | D5: No | E5: Verificar que rechaza crear una cuenta con un correo ya registrado | F5: Tener una cuenta ya creada | G5: El mismo correo usado en CP-01 | H5: 1. Pestana Crear cuenta 2. Escribir un correo ya registrado 3. Completar contrasenas 4. Click en Crear mi cuenta | I5: Muestra un mensaje de error claro en espanol y no crea la cuenta duplicada | J5: Bloquea correctamente la creacion duplicada, pero el mensaje se muestra en ingles: User already registered. Ver BUG-01. | K5: Fallido | L5: CP-02_correo_duplicado.png
A6: CP-03 | B6: Ingresar | C6: Positivo | D6: No | E6: Verificar el ingreso con correo y contrasena correctos | F6: Cuenta activa | G6: Correo y contrasena validos | H6: 1. Pestana Ingresar 2. Escribir correo y contrasena 3. Click en Ingresar a Despensalo | I6: Entra a la aplicacion y aterriza en el Resumen, igual que al crear cuenta | J6: Con sesion limpia (ventana de incognito, cuenta distinta) el ingreso aterriza correctamente en el Resumen. Sin embargo, si la sesion anterior se cerro desde Ajustes, el siguiente ingreso aterriza en Ajustes. Dado que Ajustes es la unica pantalla desde donde se puede cerrar sesion, todo ingreso posterior al primero cae en Ajustes. Ver BUG-03. | K6: Fallido | L6: CP-03_ingreso_limpio.png, CP-03_aterriza_ajustes.png
A7: CP-04 | B7: Ingresar | C7: Negativo | D7: No | E7: Verificar que rechaza una contrasena incorrecta | F7: Cuenta activa | G7: Correo valido + contrasena erronea | H7: 1. Pestana Ingresar 2. Escribir correo valido y contrasena erronea 3. Click en Ingresar a Despensalo | I7: No permite el ingreso y muestra un mensaje de error en espanol | J7: No permite el ingreso, pero el mensaje se muestra en ingles: Invalid login credentials. Ver BUG-01. | K7: Fallido | L7: CP-04_credenciales_invalidas.png
A8: CP-05 | B8: Inventario | C8: Positivo | D8: Si | E8: Verificar que se puede registrar un producto manualmente sin escanear | F8: Sesion iniciada | G8: Nombre: Arroz / Marca: Tucapel / Formato: 1 kg / Stock: 1 / Vence: 30-09-2028 | H8: 1. Click en Agregar producto sin codigo 2. Completar nombre, marca, formato, stock y fecha 3. Click en Guardar producto 4. Ir a Inventario y recargar la pagina | I8: El producto queda registrado con sus datos y persiste al recargar | J8: El producto se guarda correctamente y persiste. Observacion: el campo Codigo de barras se autogenera (manual:mtqbv8d2-uimbm8) y no es editable, por lo que no existe registro realmente sin codigo. | K8: Aprobado | L8: CP-05_form_registro.png, CP-05_producto_guardado.png, CP-05_resumen_actualizado.png
A9: CP-06 | B9: Inventario | C9: Borde | D9: Si | E9: Verificar el manejo de fechas de vencimiento invalidas o en el pasado | F9: Sesion iniciada | G9: Fecha 01-01-2020, luego 31-02-2027, luego campo vacio | H9: 1. Registrar producto con fecha 01-01-2020 y guardar 2. Registrar otro con fecha 31-02-2027 y guardar 3. Registrar otro dejando la fecha vacia 4. Revisar Inventario | I9: Acepta la fecha pasada y la marca como vencida, rechaza la fecha inexistente con un mensaje de error, y permite el campo vacio por ser opcional | J9: Fecha 01-01-2020: correcto, marca Vencido hace 2440 dias. Fecha 31-02-2027: la acepta sin error y guarda el producto SIN fecha, sin ningun aviso. Campo vacio: permitido, correcto. Ver BUG-02. | K9: Fallido | L9: CP-06_fecha_vencida.png, CP-06_fechas_invalidas.png
A10: CP-07 | B10: Escaneo | C10: Negativo | D10: Si | E10: Verificar el comportamiento al procesar un codigo de barras inexistente | F10: Sesion iniciada | G10: Codigo: 0000000000000 y luego texto: abcdef | H10: 1. Escribir el codigo en Codigo manual o lector externo 2. Click en Procesar 3. Repetir usando texto en vez de numeros | I10: Avisa que no encuentra el producto y ofrece registrarlo, sin errores de servidor | J10: Con ambos valores muestra el aviso No encontramos este codigo. Escribe el nombre una sola vez y quedara guardado, y abre el formulario Registrar producto con el codigo precargado. | K10: Aprobado | L10: CP-07_codigo_numerico.png, CP-07_codigo_texto.png
A11: CP-08 | B11: Escaneo | C11: Borde | D11: Si | E11: Verificar la validacion del campo Unidades por lectura | F11: Sesion iniciada y producto existente en inventario | G11: Valores: 0, luego -1, luego 2,5, luego 9999 | H11: 1. Cambiar Unidades por lectura a 0 2. Procesar el codigo de un producto existente 3. Repetir con -1, con 2,5 y con 9999 4. Revisar el stock resultante en Inventario | I11: Rechaza los valores invalidos con mensaje claro y el stock nunca queda fraccionario | J11: Con 0 y con -1 suma 1 unidad sin mostrar aviso alguno: descarta el valor y usa 1 por defecto. Con 2,5 suma 2,5 unidades y deja el stock fraccionario (Arroz quedo en 6,5 un.). Ver BUG-04 y BUG-05. | K11: Fallido | L11: CP-08_stock_fraccionario.png
A12: CP-09 | B12: Escaneo | C12: Negativo | D12: Si | E12: Verificar que el stock no queda negativo al usar o agotar productos | F12: Sesion iniciada y producto con stock 0 | G12: Modo Usar o agotar + valores -1 y 9999 | H12: 1. Agotar el producto Aceite desde Inventario 2. Activar el modo Usar o agotar 3. Procesar el codigo del Aceite con 9999 unidades por lectura 4. Repetir con -1 5. Revisar el stock | I12: Avisa que no hay stock disponible y el contador no baja de 0 | J12: El stock no baja de 0 con ninguno de los dos valores. La proteccion contra stock negativo funciona correctamente al restar. | K12: Aprobado | L12: CP-09_stock_no_negativo_1.png, CP-09_stock_no_negativo_2.png
A13: CP-10 | B13: Resumen / Gastos | C13: Positivo | D13: Si | E13: Verificar que los contadores del Resumen coinciden con el inventario real | F13: Sesion iniciada con productos cargados | G13: Inventario: Aceite 0 un. ($2.000), Arroz 6,5 un. ($1.240), Cuadernos 1 pack, Galletas 1 paquete | H13: 1. Anotar el contenido real de Inventario 2. Ir a Inicio 3. Comparar cada tarjeta contra lo calculado 4. Registrar cualquier diferencia | I13: PRODUCTOS 4 / UNIDADES 8,5 / STOCK BAJO 2 / AGOTADOS 1 / POR VENCER 0 / VENCIDOS 1 / VALOR DESPENSA $8.060 | J13: Los siete contadores coinciden con el inventario real: PRODUCTOS 4, UNIDADES 8,5, STOCK BAJO 2, AGOTADOS 1, POR VENCER 0, VENCIDOS 1, VALOR DESPENSA $8.060. El calculo de valor es correcto (6,5 x $1.240 = $8.060). Observacion: UNIDADES muestra 8,5 porque arrastra el stock fraccionario generado en CP-08, evidenciando que el defecto se propaga al Resumen. | K13: Aprobado | L13: CP-10_resumen_contadores.png

Sheet Bug Reports
A1: Reporte de defectos
A3: ID | B3: Titulo | C3: Caso relacionado | D3: Funcionalidad afectada | E3: Pasos de reproduccion | F3: Resultado esperado | G3: Resultado obtenido | H3: Evidencia | I3: Severidad | J3: Prioridad | K3: Ambiente | L3: Score | M3: Recomendacion de mejora
A4: BUG-01 | B4: Los mensajes de error de autenticacion se muestran en ingles | C4: CP-02, CP-04 | D4: Autenticacion | E4: 1. Abrir despensalo.cl 2. Pestana Ingresar 3. Escribir un correo valido con contrasena erronea 4. Click en Ingresar a Despensalo 5. Repetir en la pestana Crear cuenta con un correo ya registrado | F4: El mensaje de error se muestra en espanol, como el resto de la interfaz | G4: Aparecen los textos crudos del proveedor de autenticacion: Invalid login credentials y User already registered | H4: CP-02_correo_duplicado.png, CP-04_credenciales_invalidas.png | I4: Media | J4: Alta | K4: Chrome 152.0.7977.83 (64 bits) / Windows 11 / 1920x1080 | L4: =IFERROR(INDEX($B$13:$B$16,MATCH(I4,$A$13:$A$16,0))*INDEX($B$13:$B$16,MATCH(J4,$A$13:$A$16,0)),"") -> 6 | M4: Mapear los codigos de error del proveedor de autenticacion a mensajes propios en espanol. Revisar que ningun otro mensaje del sistema llegue sin traducir a la interfaz.
A5: BUG-02 | B5: El formulario acepta una fecha de vencimiento inexistente y guarda el producto sin fecha | C5: CP-06 | D5: Registro de producto | E5: 1. Ingresar a Despensalo 2. Click en Agregar producto sin codigo 3. Completar nombre y marca 4. Escribir 31-02-2027 en Fecha de vencimiento 5. Click en Guardar producto 6. Revisar el producto en Inventario | F5: El formulario rechaza la fecha inexistente y muestra un mensaje de error antes de guardar | G5: Acepta la fecha sin validarla y guarda el producto sin ninguna fecha de vencimiento, sin avisar al usuario que su dato fue descartado | H5: CP-06_fechas_invalidas.png | I5: Alta | J5: Alta | K5: Chrome 152.0.7977.83 (64 bits) / Windows 11 / 1920x1080 | L5: =IFERROR(INDEX($B$13:$B$16,MATCH(I5,$A$13:$A$16,0))*INDEX($B$13:$B$16,MATCH(J5,$A$13:$A$16,0)),"") -> 9 | M5: Validar la fecha en el formulario antes de enviar y mostrar un error explicito. Si el valor no es valido, no descartarlo en silencio: el producto queda sin alerta de vencimiento y el usuario cree que la registro.
A6: BUG-03 | B6: Tras cerrar sesion desde Ajustes, el siguiente ingreso aterriza en Ajustes en vez del Resumen | C6: CP-03 | D6: Autenticacion / Navegacion | E6: 1. Ingresar a Despensalo con credenciales validas 2. Navegar a la pantalla Ajustes 3. Cerrar sesion desde Ajustes (unica pantalla que permite cerrar sesion) 4. Volver a ingresar con las mismas credenciales 5. Observar la pantalla de destino | F6: El ingreso aterriza siempre en el Resumen, sin importar cual fue la ultima pantalla usada antes de cerrar sesion | G6: Aterriza en Ajustes. En sesion limpia (incognito, cuenta distinta) el ingreso si llega al Resumen, lo que confirma que la aplicacion restaura la ultima ruta visitada. Como Ajustes es la unica pantalla desde donde se cierra sesion, el defecto afecta a todo usuario que vuelva a entrar | H6: CP-03_ingreso_limpio.png, CP-03_aterriza_ajustes.png | I6: Media | J6: Alta | K6: Chrome 152.0.7977.83 (64 bits) / Windows 11 / 1920x1080 | L6: =IFERROR(INDEX($B$13:$B$16,MATCH(I6,$A$13:$A$16,0))*INDEX($B$13:$B$16,MATCH(J6,$A$13:$A$16,0)),"") -> 6 | M6: Limpiar la ruta persistida al cerrar sesion y forzar el destino al Resumen tras cualquier ingreso exitoso. Considerar ademas ofrecer el cierre de sesion desde el menu lateral, no solo desde Ajustes.
A7: BUG-04 | B7: Unidades por lectura acepta decimales y genera stock fraccionario | C7: CP-08 | D7: Escaneo / Inventario | E7: 1. Ingresar a Despensalo 2. En Modo de escaneo dejar activo Ingresar compra 3. Escribir 2,5 en Unidades por lectura 4. Escribir el codigo de un producto existente y click en Procesar 5. Revisar el producto en Inventario | F7: El campo rechaza los decimales cuando la unidad del producto es un., o redondea a un entero avisando al usuario | G7: Suma 2,5 unidades y el producto queda con stock fraccionario. El Arroz, cuya unidad es un., quedo con 6,5 unidades | H7: CP-08_stock_fraccionario.png | I7: Alta | J7: Alta | K7: Chrome 152.0.7977.83 (64 bits) / Windows 11 / 1920x1080 | L7: =IFERROR(INDEX($B$13:$B$16,MATCH(I7,$A$13:$A$16,0))*INDEX($B$13:$B$16,MATCH(J7,$A$13:$A$16,0)),"") -> 9 | M7: Restringir el campo a enteros cuando la unidad del producto no admite fracciones (step=1 y validacion en servidor). El stock fraccionario contamina ademas el calculo de valor en stock y el contador de unidades del Resumen.
A8: BUG-05 | B8: Los valores 0 y negativos en Unidades por lectura se reemplazan por 1 sin avisar | C8: CP-08 | D8: Escaneo | E8: 1. Ingresar a Despensalo 2. Escribir 0 en Unidades por lectura 3. Escribir el codigo de un producto existente y click en Procesar 4. Revisar el stock en Inventario 5. Repetir con -1 | F8: El campo rechaza el valor con un mensaje claro y no registra ninguna lectura | G8: Descarta el valor ingresado y suma 1 unidad sin mostrar ningun aviso. El usuario cree haber procesado 0 unidades y en realidad agrego una | H8: CP-08_stock_fraccionario.png | I8: Media | J8: Media | K8: Chrome 152.0.7977.83 (64 bits) / Windows 11 / 1920x1080 | L8: =IFERROR(INDEX($B$13:$B$16,MATCH(I8,$A$13:$A$16,0))*INDEX($B$13:$B$16,MATCH(J8,$A$13:$A$16,0)),"") -> 4 | M8: Validar el minimo en el campo (min=1) y mostrar un mensaje cuando el valor sea invalido, en lugar de sustituirlo en silencio.
A9: BUG-06 | B9: El boton de deshacer ejecuta la accion sin confirmacion previa y elimina registros | C9: SE-01 esc3 | D9: Deshacer global / Persistencia de datos | E9: 1. Ingresar a Despensalo con registros existentes 2. Presionar el boton flotante de deshacer, ubicado abajo a la izquierda del menu lateral 3. Presionarlo una segunda vez 4. Revisar el Botiquin y el Historial | F9: El boton informa que accion se va a revertir y solicita confirmacion antes de ejecutarla | G9: Ejecuta la accion de inmediato sin previo aviso. Al presionarlo dos veces se eliminaron dos registros del Botiquin de forma accidental. El unico mensaje es Ultima accion deshecha, mostrado despues de ejecutar | H9: SE-01_esc3_deshacer.png, SE-01_esc3_historial.png | I9: Alta | J9: Alta | K9: Chrome 152.0.7977.83 (64 bits) / Windows 11 / 1920x1080 | L9: =IFERROR(INDEX($B$13:$B$16,MATCH(I9,$A$13:$A$16,0))*INDEX($B$13:$B$16,MATCH(J9,$A$13:$A$16,0)),"") -> 9 | M9: Mostrar la accion concreta que se va a revertir y pedir confirmacion antes de ejecutarla. Alternativamente, ofrecer un deshacer contextual con ventana de tiempo, en vez de un boton global siempre activo que puede accionarse por error.
A10: BUG-07 | B10: El Resumen de Inicio no contabiliza los medicamentos del Botiquin, incluidos los vencidos | C10: SE-01 esc4 | D10: Resumen / Botiquin | E10: 1. Registrar en Botiquin un medicamento con fecha de vencimiento pasada 2. Ir a Inicio y revisar las tarjetas PRODUCTOS, UNIDADES y VENCIDOS 3. Comparar con el contenido real de Botiquin 4. Revisar la tabla Existencias y valor por categoria en Gastos | F10: El Resumen refleja el total de la aplicacion, alertando de todos los productos vencidos, incluidos los medicamentos | G10: El Resumen contabiliza unicamente la despensa: PRODUCTOS 4, UNIDADES 4 y VENCIDOS 1, pese a existir un medicamento vencido hace 979 dias. Gastos si suma ambas categorias (6 productos y 6 unidades) y Compras incluye medicamentos en la lista del supermercado: cada seccion aplica un criterio distinto | H10: SE-01_esc4_vencidos_inicio.png, SE-02_esc2_gastos.png, SE-02_esc1_lista_supermercado.png | I10: Alta | J10: Alta | K10: Chrome 152.0.7977.83 (64 bits) / Windows 11 / 1920x1080 | L10: =IFERROR(INDEX($B$13:$B$16,MATCH(I10,$A$13:$A$16,0))*INDEX($B$13:$B$16,MATCH(J10,$A$13:$A$16,0)),"") -> 9 | M10: Unificar el criterio de agregacion entre Resumen, Gastos y Compras. Si el Resumen debe mostrar solo la despensa, indicarlo de forma explicita e incorporar una alerta propia de medicamentos vencidos, dado que el vencimiento es mas critico en el Botiquin que en la despensa.
A11: Pesos para el score de priorizacion
A12: Nivel | B12: Peso
A13: Critica | B13: 4
A14: Alta | B14: 3
A15: Media | B15: 2
A16: Baja | B16: 1
A18: Score = peso(Severidad) x peso(Prioridad). Ordena de mayor a menor para armar la matriz priorizada de la Fase 2.

Sheet Exploratorio
A1: Testing exploratorio
A3: Sesion | B3: Funcionalidad | C3: Charter (objetivo de la sesion) | D3: Duracion | E3: Escenario explorado | F3: Accion realizada | G3: Resultado observado | H3: Es hallazgo nuevo | I3: Evidencia | J3: Nuevo caso propuesto
A4: SE-01 | B4: Botiquin | C4: Explorar el registro de medicamentos y verificar si se comporta igual que el inventario de despensa | D4: 10 min | E4: Registro de medicamento vencido | F4: Registrar Paracetamol / Lab Chile con fecha de vencimiento 01-01-2024 y revisar los contadores | G4: El Botiquin es una seccion independiente con sus propios contadores (MEDICAMENTOS, STOCK BAJO, POR VENCER, VENCIDOS). El medicamento se registra correctamente y marca Vencido hace 979 dias dentro del Botiquin | H4: No | I4: SE-01_esc1_botiquin_vencido.png
A5: SE-01 | B5: Botiquin | C5: Explorar el registro de medicamentos y verificar si se comporta igual que el inventario de despensa | D5: 10 min | E5: Mismo nombre de producto en Despensa y en Botiquin | F5: Registrar un producto llamado Arroz / Tucapel en Botiquin, existiendo ya un Arroz Tucapel en Despensa | G5: La aplicacion avisa: Ya tienes 1 registro(s) llamados «Arroz», muestra el registro existente y explica que cada marca o formato se guarda como registro independiente. El producto queda en Botiquin y no aparece en Inventario: las listas se mantienen separadas | H5: No | I5: SE-01_esc2_aviso_duplicado.png, SE-01_esc2_botiquin_2meds.png, SE-01_esc2_inventario_sin_arroz.png
A6: SE-01 | B6: Deshacer global | C6: Escenario no planificado surgido durante la sesion de Botiquin | D6: 10 min | E6: Boton flotante de deshacer | F6: Presionar dos veces seguidas el boton flotante de deshacer ubicado abajo a la izquierda | G6: El boton ejecuta la accion de inmediato, sin indicar previamente que se va a deshacer ni pedir confirmacion. Se eliminaron dos registros del Botiquin de forma accidental. El unico aviso es el mensaje posterior Ultima accion deshecha, cuando la accion ya se ejecuto | H6: Si | I6: SE-01_esc3_deshacer.png, SE-01_esc3_historial.png | J6: CP-11: verificar que el deshacer global informa la accion a revertir y solicita confirmacion antes de ejecutarla
A7: SE-02 | B7: Compras | C7: Explorar como se arma la lista de compras a partir del stock minimo | D7: 10 min | E7: Composicion de la lista de compras | F7: Revisar el contenido de la seccion Compras con productos de Despensa y de Botiquin registrados | G7: La lista, titulada Lista del supermercado, incluye los medicamentos del Botiquin junto a los productos de despensa (aparece Paracetamol Lab Chile). El Botiquin se mantiene separado en el resto de la aplicacion pero se fusiona en Compras, mezclando dos dominios distintos | H7: Si | I7: SE-02_esc1_lista_supermercado.png | J7: CP-12: verificar que la lista de compras permite distinguir o filtrar los items de Botiquin respecto de los de Despensa
A8: SE-02 | B8: Gastos | C8: Explorar el calculo de gastos y su relacion con los precios registrados | D8: 10 min | E8: Gastos frente a precios registrados | F8: Revisar la seccion Gastos teniendo productos con precio unitario ingresado manualmente | G8: Las existencias y el valor por categoria son correctos (6 productos, 6 unidades, $2.480). Sin embargo GASTO DEL MES y GASTO ACUMULADO muestran $0 pese a existir precios registrados: los gastos solo contabilizan boletas escaneadas y no los precios ingresados manualmente, sin que la interfaz lo explique | H8: Si | I8: SE-02_esc2_gastos.png | J8: CP-13: verificar que la seccion Gastos indica que solo contabiliza boletas escaneadas
A9: SE-03 | B9: Busqueda en Inventario | C9: Explorar el buscador del inventario con entradas limite y valores inesperados | D9: 10 min | E9: Mayusculas, error de tipeo y busqueda por marca | F9: Buscar ARROZ en mayusculas, luego Arrz mal escrito, luego Tucapel como marca | G9: ARROZ encuentra el producto: el buscador no distingue mayusculas de minusculas. Arrz no arroja resultados: no hay tolerancia a errores de tipeo, comportamiento esperable. Tucapel encuentra el producto, confirmando que busca por marca como anuncia el campo | H9: No | I9: SE-03_esc1_mayusculas.png, SE-03_esc1_tipeo.png, SE-03_esc1_marca.png
A10: SE-03 | B10: Busqueda en Inventario | C10: Explorar el buscador del inventario con entradas limite y valores inesperados | D10: 10 min | E10: Caracteres especiales y campo vacio | F10: Buscar <>@#$% y luego dejar el campo de busqueda vacio | G10: Con caracteres especiales muestra el mensaje No hay productos que coincidan con el filtro, sin errores ni pantalla en blanco. Con el campo vacio vuelve a listar los 4 productos. El manejo del estado sin resultados es correcto | H10: No | I10: SE-03_esc2_caracteres.png, SE-03_esc2_vacio.png
A11: SE-01 | B11: Botiquin / Resumen | C11: Escenario derivado: verificar si el Resumen de Inicio refleja los medicamentos | D11: 10 min | E11: Contadores del Inicio frente al contenido del Botiquin | F11: Registrar nuevamente Paracetamol Lab Chile con vencimiento 01-01-2024 y comparar los contadores del Inicio con el contenido real de Botiquin e Inventario | G11: El Inicio muestra PRODUCTOS 4, UNIDADES 4 y VENCIDOS 1, contabilizando solo la despensa. El Paracetamol vencido hace 979 dias no incide en ningun contador del Resumen. En cambio la seccion Gastos si suma ambas categorias (6 productos, 6 unidades) y Compras mezcla medicamentos con productos de despensa: tres secciones aplican criterios distintos | H11: Si | I11: SE-01_esc4_vencidos_inicio.png, SE-01_esc4_filtro_vencidos.png | J11: CP-14: verificar que los contadores del Resumen incluyen los medicamentos vencidos del Botiquin

Sheet Ejecuciones Auto
A1: Automatizacion
A3: Script | B3: Caso vinculado | C3: Aserciones | D3: Entorno | E3: Corrida | F3: Resultado | G3: Duracion (s) | H3: Evidencia | I3: Observaciones
A4: CP-03_ingresar.spec.js | B4: CP-03 | C4: 3 | D4: Chrome 152 escritorio 1920x1080 | E4: 1 | F4: Aprobado | G4: 5 | H4: test-results/ (trace.zip por ejecucion) | I4: Sin variacion entre corridas
A5: CP-03_ingresar.spec.js | B5: CP-03 | C5: 3 | D5: Chrome 152 escritorio 1920x1080 | E5: 2 | F5: Aprobado | G5: 4.3 | H5: test-results/ (trace.zip por ejecucion) | I5: Sin variacion entre corridas
A6: CP-03_ingresar.spec.js | B6: CP-03 | C6: 3 | D6: Chrome 152 escritorio 1920x1080 | E6: 3 | F6: Aprobado | G6: 6.4 | H6: test-results/ (trace.zip por ejecucion) | I6: Sin variacion entre corridas
A7: CP-04_ingresar_invalido.spec.js | B7: CP-04 | C7: 3 | D7: Chrome 152 escritorio 1920x1080 | E7: 1 | F7: Aprobado | G7: 4.2 | H7: test-results/ (trace.zip por ejecucion) | I7: Sin variacion entre corridas
A8: CP-04_ingresar_invalido.spec.js | B8: CP-04 | C8: 3 | D8: Chrome 152 escritorio 1920x1080 | E8: 2 | F8: Aprobado | G8: 4.1 | H8: test-results/ (trace.zip por ejecucion) | I8: Sin variacion entre corridas
A9: CP-04_ingresar_invalido.spec.js | B9: CP-04 | C9: 3 | D9: Chrome 152 escritorio 1920x1080 | E9: 3 | F9: Aprobado | G9: 5.9 | H9: test-results/ (trace.zip por ejecucion) | I9: Sin variacion entre corridas
A10: CP-07_codigo_inexistente.spec.js (numerico) | B10: CP-07 | C10: 3 | D10: Chrome 152 escritorio 1920x1080 | E10: 1 | F10: Aprobado | G10: 5.9 | H10: test-results/ (trace.zip por ejecucion) | I10: Sin variacion entre corridas
A11: CP-07_codigo_inexistente.spec.js (numerico) | B11: CP-07 | C11: 3 | D11: Chrome 152 escritorio 1920x1080 | E11: 2 | F11: Aprobado | G11: 6.1 | H11: test-results/ (trace.zip por ejecucion) | I11: Sin variacion entre corridas
A12: CP-07_codigo_inexistente.spec.js (numerico) | B12: CP-07 | C12: 3 | D12: Chrome 152 escritorio 1920x1080 | E12: 3 | F12: Aprobado | G12: 6.7 | H12: test-results/ (trace.zip por ejecucion) | I12: Sin variacion entre corridas
A13: CP-07_codigo_inexistente.spec.js (alfabetico) | B13: CP-07 | C13: 3 | D13: Chrome 152 escritorio 1920x1080 | E13: 1 | F13: Aprobado | G13: 5.6 | H13: test-results/ (trace.zip por ejecucion) | I13: Sin variacion entre corridas
A14: CP-07_codigo_inexistente.spec.js (alfabetico) | B14: CP-07 | C14: 3 | D14: Chrome 152 escritorio 1920x1080 | E14: 2 | F14: Aprobado | G14: 5.9 | H14: test-results/ (trace.zip por ejecucion) | I14: Sin variacion entre corridas
A15: CP-07_codigo_inexistente.spec.js (alfabetico) | B15: CP-07 | C15: 3 | D15: Chrome 152 escritorio 1920x1080 | E15: 3 | F15: Aprobado | G15: 5.6 | H15: test-results/ (trace.zip por ejecucion) | I15: Sin variacion entre corridas
... A27: CP-07_codigo_inexistente.spec.js (alfabetico) | B27: CP-07 | C27: 3 | D27: Chrome 152 movil 390x844 | E27: 3 | F27: Aprobado | G27: 7.4 | H27: test-results/ (trace.zip por ejecucion) | I27: Sin variacion entre corridas
A29: 24 ejecuciones: 4 tests x 2 entornos x 3 corridas. CP-07 esta parametrizado con dos codigos y genera dos tests desde un mismo script. Comando: npx playwright test --repeat-each=3

Sheet Metricas
A1: Metricas y analisis
A4: PRUEBAS MANUALES
A5: Casos disenados | B5: =COUNTA('Casos de Prueba'!A4:A13) -> 10
A6: Casos ejecutados | B6: =COUNTIF('Casos de Prueba'!K4:K13,"Aprobado")+COUNTIF('Casos de Prueba'!K4:K13,"Fallido") -> 10
A7: Casos aprobados | B7: =COUNTIF('Casos de Prueba'!K4:K13,"Aprobado") -> 5
A8: Casos fallidos | B8: =COUNTIF('Casos de Prueba'!K4:K13,"Fallido") -> 5
A9: Tasa de exito manual | B9: =IFERROR(B7/B6,0) -> 0.5 | C9: Aprobados / ejecutados
A10: Casos con sesion iniciada | B10: =COUNTIF('Casos de Prueba'!D4:D13,"Si") -> 6 | C10: La rubrica pide minimo 2
A11: Casos negativos o de borde | B11: =COUNTIF('Casos de Prueba'!C4:C13,"Negativo")+COUNTIF('Casos de Prueba'!C4:C13,"Borde") -> 6 | C11: La rubrica pide minimo 2
A13: DEFECTOS
A14: Defectos documentados | B14: =COUNTIF('Bug Reports'!B4:B10,"?*") -> 7 | C14: Metrica 2. La rubrica pide minimo 3
A15: Defectos severidad Alta o Critica | B15: =COUNTIF('Bug Reports'!I4:I10,"Critica")+COUNTIF('Bug Reports'!I4:I10,"Alta") -> 4
A16: Densidad de defectos por caso ejecutado | B16: =IFERROR(B14/B6,0) -> 0.7 | C16: Defectos por caso ejecutado
A18: EXPLORATORIO
A19: Escenarios explorados | B19: =COUNTIF(Exploratorio!E4:E11,"?*") -> 8 | C19: La rubrica pide minimo 6
A20: Hallazgos nuevos | B20: =COUNTIF(Exploratorio!H4:H11,"Si") -> 4 | C20: Metrica 4. Minimo 2
A22: AUTOMATIZACION
A23: Ejecuciones automatizadas | B23: =COUNTIF('Ejecuciones Auto'!F4:F27,"Aprobado")+COUNTIF('Ejecuciones Auto'!F4:F27,"Fallido") -> 24
A24: Ejecuciones aprobadas | B24: =COUNTIF('Ejecuciones Auto'!F4:F27,"Aprobado") -> 24
A25: Tasa de consistencia automatizada | B25: =IFERROR(B24/B23,0) -> 1 | C25: Ejecuciones con resultado repetible
A26: Duracion promedio por ejecucion (s) | B26: =IFERROR(AVERAGE('Ejecuciones Auto'!G4:G27),0) -> 6.1291667 | C26: Metrica 6
A27: Total de aserciones implementadas | B27: =SUM('Ejecuciones Auto'!C4:C27) -> 72
A29: TENDENCIAS Y RECOMENDACIONES
A30: Tendencia 1 | B30: Ningun mensaje del sistema de autenticacion esta traducido: los textos del proveedor llegan crudos a la interfaz (BUG-01).
A31: Tendencia 2 | B31: La validacion de entradas ocurre despues de guardar, no antes: valores invalidos se aceptan y se corrigen o descartan en silencio (BUG-02, BUG-04, BUG-05).
A32: Tendencia 3 | B32: La proteccion existe al restar stock pero no al sumarlo: el stock nunca baja de 0 (CP-09), pero admite decimales al ingresar (BUG-04).
A33: Tendencia 4 | B33: Las acciones que modifican o eliminan datos se ejecutan sin confirmacion: el boton de deshacer borra registros al primer clic (BUG-06) y los valores invalidos se descartan en silencio (BUG-02, BUG-05). El usuario no controla ni percibe los cambios sobre sus datos.
A34: Tendencia 5 | B34: No hay un criterio unico de agregacion entre secciones: el Resumen contabiliza solo la despensa, Gastos suma despensa y botiquin, y Compras mezcla ambas en una sola lista (BUG-07). El mismo dato arroja tres totales distintos segun donde se consulte.
A35: Recomendacion 1 | B35: Validar en el formulario antes de enviar: fecha real, minimo 1 y solo enteros cuando la unidad no admite fracciones. Cubre BUG-02, BUG-04 y BUG-05.
A36: Recomendacion 2 | B36: Traducir los errores de autenticacion a mensajes propios en espanol. Cubre BUG-01.
A37: Recomendacion 3 | B37: Nunca descartar un dato del usuario en silencio: si un valor no es valido, avisarlo en pantalla.
A38: Comparacion manual vs automatizado | B38: Las pruebas manuales dieron 50% de exito y las automatizadas 100%. La diferencia no indica mejora del software: los scripts verifican el comportamiento ya observado, no el esperado. CP-04 aprueba confirmando que el mensaje sale en ingles, que es justamente BUG-01. La automatizacion mide estabilidad; los defectos se detectan en la ejecucion manual y en la exploracion.
